autora/experimentalist/falsification/__init__.py
autora/experimentalist/falsification/popper_net.py
autora/experimentalist/falsification/utils.py
autora_experimentalist_falsification-2.2.0.dist-info/LICENSE
autora_experimentalist_falsification-2.2.0.dist-info/METADATA
autora_experimentalist_falsification-2.2.0.dist-info/WHEEL
autora_experimentalist_falsification-2.2.0.dist-info/top_level.txt
autora_experimentalist_falsification-2.2.0.dist-info/RECORD
