Metadata-Version: 2.1
Name: autora-experimentalist-falsification
Version: 2.2.0
Summary: AutoRA Falsification Experimentalist
Author-email: Sebastian Musslick <sebastian@musslick.de>
License: MIT License
Project-URL: homepage, http://www.empiricalresearch.ai
Project-URL: repository, https://github.com/AutoResearch/autora-experimentalist-falsification
Project-URL: documentation, https://autoresearch.github.io/autora/
License-File: LICENSE
Requires-Dist: autora-core >=3.1.0
Requires-Dist: torch
Requires-Dist: pandas
Requires-Dist: numpy <2,>=1
Provides-Extra: dev
Requires-Dist: autora-core[dev] ; extra == 'dev'
